lumi_gateway/__init__.py
tests/__init__.py
tests/conftest.py
tests/gateway.py
tests/test_e2e.py
PyLumiGateway-0.12.3.dist-info/METADATA
PyLumiGateway-0.12.3.dist-info/WHEEL
PyLumiGateway-0.12.3.dist-info/top_level.txt
PyLumiGateway-0.12.3.dist-info/RECORD
