Metadata-Version: 2.1
Name: PyLumiGateway
Version: 0.12.3
Summary: A library to communicate with the Lumi Gateway
Home-page: https://github.com/Danielhiversen/PyXiaomiGateway/
Author: Serkan Yilmaz
Author-email: onlytango@gmail.com
License: UNKNOWN
Platform: UNKNOWN
Classifier: Development Status :: 3 - Alpha
Classifier: Environment :: Other Environment
Classifier: Intended Audience :: Developers
Classifier: Operating System :: OS Independent
Classifier: Programming Language :: Python
Classifier: Topic :: Home Automation
Classifier: Topic :: Software Development :: Libraries :: Python Modules
Requires-Dist: cryptography (>=2.1.1)
